pkg_deps/__init__.py
pkg_deps/annotators.py
pkg_deps/collector.py
pkg_deps/main.py
pkg_deps/probe.py
pkg_deps/writers.py
pkg_deps-1.0.3.dist-info/DESCRIPTION.rst
pkg_deps-1.0.3.dist-info/METADATA
pkg_deps-1.0.3.dist-info/RECORD
pkg_deps-1.0.3.dist-info/WHEEL
pkg_deps-1.0.3.dist-info/entry_points.txt
pkg_deps-1.0.3.dist-info/metadata.json
pkg_deps-1.0.3.dist-info/top_level.txt
tests/__init__.py
tests/tests.py
