Metadata-Version: 2.0
Name: pkg-deps
Version: 1.0.3
Summary: Print dependency info in graph form and check for problems
Home-page: https://github.com/tgs/pkg-deps
Author: UNKNOWN
Author-email: UNKNOWN
License: Public Domain
Platform: UNKNOWN
Requires-Dist: pydotplus
Requires-Dist: networkx (<2)
Requires-Dist: click
Provides-Extra: teamcity
Requires-Dist: teamcity-messages; extra == 'teamcity'
